bloqs/__init__.py
bloqs/common/QuantumGate.py
bloqs/common/__init__.py
bloqs/ext/cirq/__init__.py
bloqs/ext/cirq/gates.py
bloqs/ext/cirq/utils.py
bloqs/ext/pyquil/__init__.py
bloqs/ext/pyquil/gates.py
bloqs/ext/pyquil/utils.py
bloqs-0.0.2.dist-info/LICENSE
bloqs-0.0.2.dist-info/METADATA
bloqs-0.0.2.dist-info/WHEEL
bloqs-0.0.2.dist-info/top_level.txt
bloqs-0.0.2.dist-info/RECORD
