Metadata-Version: 2.1
Name: bloqs
Version: 0.0.2
Summary: A small utility library for Qiskit quantum gates in Cirq and pyQuil
Author-email: Arfat Salman <giney.paradise@gmail.com>
Project-URL: Homepage, https://github.com/pypa/sampleproject
Project-URL: Bug Tracker, https://github.com/pypa/sampleproject/issues
Classifier: Programming Language :: Python :: 3
Classifier: License :: OSI Approved :: MIT License
Classifier: Operating System :: OS Independent
Requires-Python: >=3.7
License-File: LICENSE
Requires-Dist: cirq
Requires-Dist: pyquil
